ipynb-image-extractor/__init__.py
ipynb-image-extractor/extractor.py
ipynb_image_extract/__init__.py
ipynb_image_extract/extractor.py
ipynb_image_extractor/__init__.py
ipynb_image_extractor/extractor.py
ipynb_image_extract-1.0.dist-info/LICENSE
ipynb_image_extract-1.0.dist-info/METADATA
ipynb_image_extract-1.0.dist-info/WHEEL
ipynb_image_extract-1.0.dist-info/entry_points.txt
ipynb_image_extract-1.0.dist-info/top_level.txt
ipynb_image_extract-1.0.dist-info/RECORD
