Metadata-Version: 2.1
Name: ipynb-image-extract
Version: 1.0
Summary: Extract images from IPython Notebooks
Author: Rohan Sanjeev Pothuru
Author-email: rohan.mbox@gmail.com
License-File: LICENSE
Requires-Dist: nbformat
Requires-Dist: Pillow
